aiconfig/ChatCompletion.py
aiconfig/Config.py
aiconfig/__init__.py
aiconfig/callback.py
aiconfig/model_parser.py
aiconfig/registry.py
aiconfig/schema.py
aiconfig/default_parsers/__init__.py
aiconfig/default_parsers/anyscale_endpoint.py
aiconfig/default_parsers/azure.py
aiconfig/default_parsers/claude.py
aiconfig/default_parsers/dalle.py
aiconfig/default_parsers/gemini.py
aiconfig/default_parsers/hf.py
aiconfig/default_parsers/openai.py
aiconfig/default_parsers/openai_vision.py
aiconfig/default_parsers/palm.py
aiconfig/default_parsers/parameterized_model_parser.py
aiconfig/editor/__init__.py
aiconfig/editor/example_aiconfig_model_registry.py
aiconfig/editor/client/__init__.py
aiconfig/editor/client/node_modules/flatted/python/flatted.py
aiconfig/editor/client/node_modules/flatted/python/test.py
aiconfig/editor/server/__init__.py
aiconfig/editor/server/eval_server_utils.py
aiconfig/editor/server/queue_iterator.py
aiconfig/editor/server/server.py
aiconfig/editor/server/server_file_utils.py
aiconfig/editor/server/server_utils.py
aiconfig/editor/server/static/asset-manifest.json
aiconfig/editor/server/static/index.html
aiconfig/editor/server/static/manifest.json
aiconfig/editor/server/static/robots.txt
aiconfig/editor/server/static/images/aiconfigLogo.png
aiconfig/editor/server/static/static/js/302.6a4a934a.chunk.js
aiconfig/editor/server/static/static/js/302.6a4a934a.chunk.js.map
aiconfig/editor/server/static/static/js/450.3ec30143.chunk.js
aiconfig/editor/server/static/static/js/450.3ec30143.chunk.js.map
aiconfig/editor/server/static/static/js/647.2d46acf1.chunk.js
aiconfig/editor/server/static/static/js/647.2d46acf1.chunk.js.map
aiconfig/editor/server/static/static/js/main.b527ce8a.js
aiconfig/editor/server/static/static/js/main.b527ce8a.js.LICENSE.txt
aiconfig/editor/server/static/static/js/main.b527ce8a.js.map
aiconfig/eval/__init__.py
aiconfig/eval/common.py
aiconfig/eval/lib.py
aiconfig/eval/metrics.py
aiconfig/eval/openai.py
aiconfig/eval/api/__init__.py
lm_debug_eval_ui-0.0.6.dist-info/LICENSE
lm_debug_eval_ui-0.0.6.dist-info/METADATA
lm_debug_eval_ui-0.0.6.dist-info/WHEEL
lm_debug_eval_ui-0.0.6.dist-info/entry_points.txt
lm_debug_eval_ui-0.0.6.dist-info/top_level.txt
lm_debug_eval_ui-0.0.6.dist-info/RECORD
