Metadata-Version: 2.1
Name: lm-debug-eval-ui
Version: 0.0.6
Summary: LLM Application Debug/Eval UI on top of AIConfig
Author: LastMile AI
Project-URL: Homepage, https://github.com/lastmile-ai/aiconfig
Classifier: Intended Audience :: Developers
Classifier: Programming Language :: Python :: 3
Requires-Python: >=3.10
License-File: LICENSE
Requires-Dist: anthropic-bedrock
Requires-Dist: black
Requires-Dist: flake8
Requires-Dist: flask-cors
Requires-Dist: flask[async]
Requires-Dist: frozendict
Requires-Dist: google-generativeai >=0.3.1
Requires-Dist: huggingface-hub >=0.20.3
Requires-Dist: hypothesis ==6.91.0
Requires-Dist: lastmile-utils ==0.0.23
Requires-Dist: mock
Requires-Dist: nest-asyncio
Requires-Dist: nltk
Requires-Dist: openai >=1.13.3
Requires-Dist: prompt-toolkit
Requires-Dist: pybars3
Requires-Dist: pydantic >=2.1
Requires-Dist: pylint
Requires-Dist: pytest
Requires-Dist: pytest-asyncio
Requires-Dist: python-dotenv
Requires-Dist: pyyaml
Requires-Dist: requests
Requires-Dist: result
Requires-Dist: ruamel.yaml
Requires-Dist: peewee ==3.17.1
